itvalleysecurity/__init__.py
itvalleysecurity/config.py
itvalleysecurity/core.py
itvalleysecurity/exceptions.py
itvalleysecurity/py.typed
itvalleysecurity/typing.py
itvalleysecurity/utils.py
itvalleysecurity/fastapi/__init__.py
itvalleysecurity/fastapi/cookies.py
itvalleysecurity/fastapi/deps.py
itvalleysecurity/fastapi/endpoints.py
itvalleysecurity/fastapi/payloads.py
itvalleysecurity-0.1.0.dist-info/licenses/LICENSE
itvalleysecurity-0.1.0.dist-info/METADATA
itvalleysecurity-0.1.0.dist-info/WHEEL
itvalleysecurity-0.1.0.dist-info/top_level.txt
itvalleysecurity-0.1.0.dist-info/RECORD
