Metadata-Version: 2.4
Name: itvalleysecurity
Version: 0.1.0
Summary: SDK de segurança JWT plug-and-play (Header ou HttpOnly Cookie)
Home-page: https://github.com/itvalley/itvalleysecurity
Author: IT Valley School
Author-email: Carlos Viana <contato@itvalley.com.br>
Maintainer-email: IT Valley School <contato@itvalley.com.br>
License: MIT
Project-URL: Homepage, https://github.com/itvalley/itvalleysecurity
Project-URL: Documentation, https://github.com/itvalley/itvalleysecurity#readme
Project-URL: Repository, https://github.com/itvalley/itvalleysecurity.git
Project-URL: Bug Tracker, https://github.com/itvalley/itvalleysecurity/issues
Project-URL: Changelog, https://github.com/itvalley/itvalleysecurity/blob/main/CHANGELOG.md
Keywords: jwt,authentication,fastapi,security,token,oauth,bearer,cookie
Classifier: Development Status :: 4 - Beta
Classifier: Intended Audience :: Developers
Classifier: License :: OSI Approved :: MIT License
Classifier: Operating System :: OS Independent
Classifier: Programming Language :: Python :: 3
Classifier: Programming Language :: Python :: 3.10
Classifier: Programming Language :: Python :: 3.11
Classifier: Programming Language :: Python :: 3.12
Classifier: Topic :: Internet :: WWW/HTTP
Classifier: Topic :: Security
Classifier: Topic :: Software Development :: Libraries :: Python Modules
Classifier: Framework :: FastAPI
Requires-Python: >=3.10
License-File: LICENSE
Requires-Dist: PyJWT<3,>=2.9.0
Requires-Dist: python-dotenv>=1.0.1
Requires-Dist: fastapi>=0.111
Requires-Dist: pydantic[email]>=2.0
Provides-Extra: tests
Requires-Dist: pytest>=8; extra == "tests"
Requires-Dist: pytest-cov; extra == "tests"
Provides-Extra: dev
Requires-Dist: pytest>=8; extra == "dev"
Requires-Dist: pytest-cov; extra == "dev"
Requires-Dist: black; extra == "dev"
Requires-Dist: flake8; extra == "dev"
Requires-Dist: mypy; extra == "dev"
Requires-Dist: pre-commit; extra == "dev"
Dynamic: license-file
